kharazmi/__init__.py
kharazmi/__main__.py
kharazmi/exceptions.py
kharazmi/lexer.py
kharazmi/models.py
kharazmi/parser.py
kharazmi/py.typed
kharazmi/types.py
kharazmi-0.1.4.dist-info/AUTHORS.md
kharazmi-0.1.4.dist-info/LICENSE
kharazmi-0.1.4.dist-info/METADATA
kharazmi-0.1.4.dist-info/WHEEL
kharazmi-0.1.4.dist-info/top_level.txt
kharazmi-0.1.4.dist-info/zip-safe
kharazmi-0.1.4.dist-info/RECORD
