Metadata-Version: 2.1
Name: kharazmi
Version: 0.1.4
Summary: An equation parser/calculator module for python.
Home-page: https://github.com/mmohaveri/kharazmi
Author: Mahdi Mohaveri
Author-email: mmohaveri@gmail.com
License: MIT License
Keywords: development,expression,algebra,equation
Platform: UNKNOWN
Classifier: Development Status :: 3 - Alpha
Classifier: Intended Audience :: Developers
Classifier: License :: OSI Approved :: MIT License
Classifier: Operating System :: OS Independent
Classifier: Programming Language :: Python :: 3
Classifier: Programming Language :: Python :: 3 :: Only
Classifier: Programming Language :: Python :: 3.6
Classifier: Programming Language :: Python :: 3.7
Classifier: Programming Language :: Python :: 3.8
Classifier: Topic :: Software Development
Classifier: Topic :: Utilities
Classifier: Typing :: Typed
Requires-Python: >=3.6
License-File: LICENSE
License-File: AUTHORS.md
Requires-Dist: sly (>=0.4)
